Workbook
Name address: RFELINK!$C$2
Name amount: [1]RFELINK!#REF!
Name amount: RFELINK!#REF!
Name architect: [2]RFELINK!$U$2
Name architect: RFELINK!$U$2
Name basejobfee: RFELINK!$M$2
Name basejobgc: RFELINK!$K$2
Name basejobins: RFELINK!$L$2
Name client: RFELINK!$S$2
Name cofee: RFELINK!$P$2
Name cogc: RFELINK!$N$2
Name coins: RFELINK!$O$2
Name contacts: [2]RFELINK!$A$9:$P$4051
Name contacts: RFELINK!$A$9:$P$1006
Name conum: [2]RFELINK!$AI$2
Name conum: RFELINK!#REF!
Name CreateDate: RFELINK!$G$2
Name datetyped: [1]RFELINK!#REF!
Name datetyped: RFELINK!#REF!
Name Demolition: '[3]Budget Breakdown'!$A$9:$IV$67
Name Demolition: Estimate!$8:$62
Name DueDate: RFELINK!$I$2
Name engineer: RFELINK!$V$2
Name Estimator: RFELINK!$H$2
Name Executive: [2]RFELINK!$AE$2
Name Executive: RFELINK!$Y$2
Name Expeditor: [1]RFELINK!#REF!
Name Expeditor: RFELINK!#REF!
Name Floor: RFELINK!$D$2
Name From: RFELINK!$F$2
Name JobNum: [2]RFELINK!$E$2
Name JobNum: RFELINK!$E$2
Name location: [1]RFELINK!#REF!
Name location: RFELINK!#REF!
Name NAME: '[3]Budget Breakdown'!#REF!
Name NAME: 'General Conditions'!$D$2
Name NAME: Estimate!#REF!
Name NAME: Estimate!#REF!
Name projectmgr: [2]RFELINK!$AF$2
Name Projectmgr: RFELINK!$Z$2
Name PropName: RFELINK!$B$2
Name PropNum: [2]RFELINK!$A$2
Name PropNum: RFELINK!$A$2
Name Proposal: '[4]Budget Breakdown'!#REF!
Name Proposal: '[4]Budget Breakdown'!#REF!
Name regsf: [1]RFELINK!$AC$2
Name regsf: RFELINK!$AC$2
Name remarks: RFELINK!$AD$2
Name rentablesf: [1]RFELINK!#REF!
Name rentablesf: RFELINK!#REF!
Name representative: RFELINK!$T$2
Name RFE: RFELINK!$A$1:$AD$3
Name RFE_From_Access_to_Excel: RFELINK!$A$1:$V$2
Name RFEContacts: RFELINK!$A$9:$R$1006
Name rfetype: RFELINK!$J$2
Name Summary2: '[3]Budget Breakdown'!$D$2
Name Summary2: Estimate!$D$2
Name typerequest: [2]RFELINK!$AG$2
Name TypeRequest: RFELINK!$AA$2
Name usablesf: [2]RFELINK!$Q$2

Sheet RFE
C2: REQUEST FOR | E2: SOURCE:
C3: ESTIMATE | E3: INITIATED DATE:
C4: =+C8 -> Town House Renovation | F4: 24-038C
E7: ESTIMATOR
B8: NAME: | C8: Town House Renovation
B9: ADDRESS : | C9: 60 Bank Street | E9: PROJ. EXEC.
B10: CITY/STATE: | C10: New York, NY 10014
B11: FLOOR : | E11: PROJ. MGR.
E12: =VLOOKUP(Projectmgr,contacts,3,FALSE) -> #N/A | F12: =VLOOKUP([5]RFELINK!F5,contacts,4,FALSE) -> #N/A
B13: SEND PROPOSAL TO (Client or Owners Rep) | E13: PROPOSAL NO.
B14: Owners Rep: | C14: Sawicki/Tarella Architectur +Design, P.C. | E14: =+F4 -> 24-038C
B15: ADDRESS: | C15: 303 West 13th Street | E15: DUE DATE:
C16: New York. NY 10014 | E16: 7/290
B17: ATTENTION: | C17: Joseph S. Tarella / Edward Bowser; | E17: TYPE OF ESTIMATE
B18: PHONE: | C18: 212-473-4000 | E18: Budget
B19: EMAIL: | C19: jtarella@sawickitarella.com; ebowser@sawickitarella.com | E19: Mark Up
E20: Gen. Cond. | F20: 0.0725
B21: Client: | E21: Insurance | F21: 0.025
B22: ADDRESS: | E22: Fee | F22: 0.0325
E23: Useable Square Footage
B24: ATTENTION: | E24: 6000
B25: PHONE: | E25: Rentable Square Footage
B26: EMAIL: | E26: =regsf -> 0
B28: Architectural Firm: | E28: Building Info:
B29: Address | E29: Super:
E30: Contact #
B31: Phone | E31: Bld Manager
B32: EMAIL: | E32: Contact #
B33: Contact | E33: Email:
C36: Required/Provided | E36: Yes or No | F36: By Whom
C37: JOB SCHEDULE
C38: BOOK
C39: BULDING RULES
C40: LANDLORD APPROVED SUBS
C41: UNION OR NON UNION
C42: SITE VISIT
C43: BID FORM
C44: DUE FOR SUBS | E44: date?
B45: Projct Desciption:
B48: Outcome:
E51: TO BE REVIEWED BY:

Sheet RFELINK

Sheet CVR LETTER
B10: 45965 | H10: Proposal # | I10: =+RFE!E14 -> 24-038C
B12: =+RFE!C17 -> Joseph S. Tarella / Edward Bowser;
B13: =+RFE!C14 -> Sawicki/Tarella Architectur +Design, P.C.
B14: =+RFE!C15 -> 303 West 13th Street
B15: =+RFE!C16 -> New York. NY 10014
B17: Re: | C17: =+RFE!C8 -> Town House Renovation
C18: =+RFE!C9 -> 60 Bank Street
C19: =+RFE!C10 -> New York, NY 10014
B22: =CONCATENATE("Dear ",+RFE!C17) -> Dear Joseph S. Tarella / Edward Bowser;
B24: Enclosed please find DNP Builders, LLC d/b/a O+D Builders revised proposal for the work at the above noted project.
B27: Should you have any questions or require any additional information regarding this proposal, please do not hesitate to contact me.
B30: Sincerely,
B35: Antonio Tutino
B36: Managing Member/CEO
B37: O+D Builders,LLC

Sheet Summary Sheet 
B2: =RFE!C8 -> Town House Renovation | C2: Proposal # : | E2: =+RFE!E14 -> 24-038C
B3: =RFE!C9 -> 60 Bank Street | C3: Rev. | E3: 11/4/2025
B4: =RFE!C10 -> New York, NY 10014
B5: Proposal
A8: DIVISION | B8: CSI | D8: 45897 | E8: Amount | F8: Delta | G8: Comments
A10: =+'Bid Comparison '!A10 -> 1050 | B10: =+'Bid Comparison '!B10 -> General Requirements | D10: 448250 | E10: =+'Bid Comparison '!E10 -> 364800 | F10: =+E10-D10 -> -83450 | G10: PM & Est to GCs
A11: =+'Bid Comparison '!A11 -> 1100 | B11: =+'Bid Comparison '!B11 -> Protection & Logistics | D11: 154500 | E11: =+'Bid Comparison '!E11 -> 122000 | F11: =+E11-D11 -> -32500
A12: =+'Bid Comparison '!A12 -> 2000 | B12: =+'Bid Comparison '!B12 -> Excavation/Foundation | D12: 586511 | E12: =+'Bid Comparison '!E12 -> 550000 | F12: =+E12-D12 -> -36511
A13: =+'Bid Comparison '!A13 -> 2010 | B13: =+'Bid Comparison '!B13 -> Underpinning, Shoring & Support of Excavation | D13: 460393 | E13: =+'Bid Comparison '!E13 -> 420000 | F13: =+E13-D13 -> -40393
B14: =+'Bid Comparison '!B14 -> Waterproofing | D14: 99130 | E14: =+'Bid Comparison '!E14 -> 95000 | F14: =+E14-D14 -> -4130
A15: =+'Bid Comparison '!A15 -> 2050 | B15: =+'Bid Comparison '!B15 -> Demolition | D15: 198300 | E15: =+'Bid Comparison '!E15 -> 178300 | F15: =+E15-D15 -> -20000
A16: =+'Bid Comparison '!A16 -> 2090 | B16: =+'Bid Comparison '!B16 -> Asbestos Removal | D16: Not Included | E16: =+'Bid Comparison '!E16 -> Not Included
A17: 2100 | B17: Site Work | D17: 76775 | E17: =+'Bid Comparison '!E17 -> 76775 | F17: =+E17-D17 -> 0
A18: =+'Bid Comparison '!A18 -> 3000 | B18: =+'Bid Comparison '!B18 -> Concrete | D18: 26000 | E18: =+'Bid Comparison '!E18 -> 26000 | F18: =+E18-D18 -> 0
A19: =+'Bid Comparison '!A19 -> 4000 | B19: =+'Bid Comparison '!B19 -> Masonry | D19: 66000 | E19: =+'Bid Comparison '!E19-E20 -> 63750 | F19: =+E19-D19 -> -2250
B20: =+Estimate!C88 -> Interior Masonry Remediation | D20: 84850 | E20: =+Estimate!I94 -> 77600 | F20: =+E20-D20 -> -7250
A21: =+'Bid Comparison '!A20 -> 4500 | B21: =+'Bid Comparison '!B20 -> Masonry Restoration | D21: 112750 | E21: =+'Bid Comparison '!E20 -> 66875 | F21: =+E21-D21 -> -45875
A22: =+'Bid Comparison '!A21 -> 5120 | B22: =+'Bid Comparison '!B21 -> Structural Steel | D22: 295000 | E22: =+'Bid Comparison '!E21 -> 238500 | F22: =+E22-D22 -> -56500
A23: =+'Bid Comparison '!A22 -> 5400 | B23: =+'Bid Comparison '!B22 -> Ornamental Iron Works | D23: 80750 | E23: =+'Bid Comparison '!E22 -> 70750 | F23: =+E23-D23 -> -10000
A24: =+'Bid Comparison '!A23 -> 5500 | B24: =+'Bid Comparison '!B23 -> Miscellaneous Iron | D24: 35000 | E24: =+'Bid Comparison '!E23 -> 24800 | F24: =+E24-D24 -> -10200
A25: =+'Bid Comparison '!A24 -> 6400 | B25: =+'Bid Comparison '!B24 -> Architectural Woodwork | D25: 54350 | E25: =+'Bid Comparison '!E24 -> 54350 | F25: =+E25-D25 -> 0
A26: =+'Bid Comparison '!A25 -> 6500 | B26: =+'Bid Comparison '!B25 -> Rough Carpentry | D26: 245560 | E26: =+'Bid Comparison '!E25 -> 238060 | F26: =+E26-D26 -> -7500
A27: =+'Bid Comparison '!A26 -> 0 | B27: =+'Bid Comparison '!B26 -> Finish Carpentry | D27: 25000 | E27: =+'Bid Comparison '!E26 -> 25000 | F27: =+E27-D27 -> 0
A28: =+'Bid Comparison '!A27 -> 7500 | B28: =+'Bid Comparison '!B27 -> Roofing/Waterproofing | D28: 102475 | E28: =+'Bid Comparison '!E27 -> 45975 | F28: =+E28-D28 -> -56500
A29: =+'Bid Comparison '!A28 -> 8110 | B29: =+'Bid Comparison '!B28 -> Doors, Frames & Hardware | D29: See Alternate | E29: =+'Bid Comparison '!E28 -> See Alternate
A30: =+'Bid Comparison '!A29 -> 0 | B30: Finish Hardware -Locksets & Levers | D30: By Others | E30: =+'Bid Comparison '!E29 -> By Others
A31: =+'Bid Comparison '!A30 -> 8520 | B31: =+'Bid Comparison '!B30 -> Wood Windows | D31: 90000 | E31: =+'Bid Comparison '!E30 -> 45000 | F31: =+E31-D31 -> -45000
A32: =+'Bid Comparison '!A31 -> 8800 | B32: =+'Bid Comparison '!B31 -> Architectural Metal & Glass | D32: 229540 | E32: =+'Bid Comparison '!E31 -> 12200 | F32: =+E32-D32 -> -217340
A33: =+'Bid Comparison '!A32 -> 8810 | B33: =+'Bid Comparison '!B32 -> Window Film | D33: 7000 | E33: =+'Bid Comparison '!E32 -> Alternate | F33: =-D33 -> -7000
A34: =+'Bid Comparison '!A33 -> 8900 | B34: =+'Bid Comparison '!B33 -> Window Walls | D34: Alternate | E34: =+'Bid Comparison '!E33 -> Alternate
A35: =+'Bid Comparison '!A35 -> 9250 | B35: =+'Bid Comparison '!B35 -> Drywall & Carpentry | D35: 226376 | E35: =+'Bid Comparison '!E35 -> 214976 | F35: =+E35-D35 -> -11400
A36: =+'Bid Comparison '!A36 -> 9300 | B36: Stone & Tile | C36: Install only Materials are FBO | D36: 68575 | E36: =+'Bid Comparison '!E36 -> 67075 | F36: =+E36-D36 -> -1500
A37: =+'Bid Comparison '!A37 -> 9550 | B37: =+'Bid Comparison '!B37 -> Wood Flooring | D37: 127603 | E37: =+'Bid Comparison '!E37 -> 116853 | F37: =+E37-D37 -> -10750
B38: =+'Bid Comparison '!B38 -> Specialty Finishes | D38: 58098 | E38: =+'Bid Comparison '!E38 -> 55610 | F38: =+E38-D38 -> -2488
B39: =+'Bid Comparison '!B39 -> Artisan Plaster | D39: 131670 | E39: =+'Bid Comparison '!E39 -> 120650 | F39: =+E39-D39 -> -11020
A40: =+'Bid Comparison '!A40 -> 9900 | B40: =+'Bid Comparison '!B40 -> Painting | D40: 48000 | E40: =+'Bid Comparison '!E40 -> 45000 | F40: =+E40-D40 -> -3000
A41: =+'Bid Comparison '!A41 -> 10800 | B41: =+'Bid Comparison '!B41 -> Toilet Accessories | D41: Furnished By the Owner | E41: Furnished By the Owner
A42: =+'Bid Comparison '!A42 -> 11450 | B42: =+'Bid Comparison '!B42 -> Appliances | C42: (set in place only) | D42: 10000 | E42: 0 | F42: =+E42-D42 -> -10000
A43: =+'Bid Comparison '!A43 -> 11750 | B43: =+'Bid Comparison '!B43 -> Fireplace | D43: 12500 | E43: FBO | F43: =-D43 -> -12500
A44: =+'Bid Comparison '!A44 -> 12500 | B44: =+'Bid Comparison '!B44 -> Window Treatment | D44: By Others | E44: =+'Bid Comparison '!E44 -> By Others
A45: 13500 | B45: Sauna & Steam Room | D45: FBO | E45: Furnished By the Owner
B46: Fireplace | F46: =+E46-D46 -> 0
A47: =+'Bid Comparison '!A46 -> 14200 | B47: =+'Bid Comparison '!B46 -> Elevator Work | D47: 124750 | E47: =+'Bid Comparison '!E46 -> 124750 | F47: =+E47-D47 -> 0
A48: =+'Bid Comparison '!A50 -> 15600 | B48: =+'Bid Comparison '!B50 -> HVAC | D48: 510000 | E48: =+'Bid Comparison '!E50 -> 495000 | F48: =+E48-D48 -> -15000
A49: =+'Bid Comparison '!A47 -> 15400 | B49: =+'Bid Comparison '!B47 -> Plumbing | D49: 370000 | E49: =+'Bid Comparison '!E47 -> 315000 | F49: =+E49-D49 -> -55000
A50: =+'Bid Comparison '!A48 -> 15450 | B50: =+'Bid Comparison '!B48 -> Plumbing Fixtures | D50: FBO | E50: =+'Bid Comparison '!E48 -> Furnished By the Owner
A51: =+'Bid Comparison '!A49 -> 15500 | B51: =+'Bid Comparison '!B49 -> Sprinklers | D51: 76400 | E51: =+'Bid Comparison '!E49 -> 70400 | F51: =+E51-D51 -> -6000
A52: =+'Bid Comparison '!A51 -> 16000 | B52: =+'Bid Comparison '!B51 -> Electric | D52: 285900 | E52: =+'Bid Comparison '!E51 -> 192900 | F52: =+E52-D52 -> -93000
A53: =+'Bid Comparison '!A52 -> 0 | B53: =+'Bid Comparison '!B52 -> Electric Radiant Heat | D53: 168700 | E53: =+'Bid Comparison '!E52 -> 168700 | F53: =+E53-D53 -> 0
A54: =+'Bid Comparison '!A57 -> 16500 | B54: =+'Bid Comparison '!B57 -> Light Fixtures | D54: Furnished By the Owner | E54: Furnished By the Owner
A55: =+'Bid Comparison '!A56 -> 16300 | B55: =+'Bid Comparison '!B56 -> Communications Cabling | D55: By Others | E55: =+'Bid Comparison '!E56 -> By Others
A56: =+'Bid Comparison '!A58 -> 17300 | B56: =+'Bid Comparison '!B58 -> Security Systems | D56: By Others | E56: =+'Bid Comparison '!E58 -> By Others
B57: Sub-Total Construction Costs | D57: 5704706 | E57: =SUM(E10:E56) -> 4782649 | F57: =+E57-D57 -> -922057
B58: General Conditions | D58: 470638.24 | E58: =+E57*RFE!F20 -> 346742.05 | F58: =+E58-D58 -> -123896.19 | H58: =+E58+E10 -> 711542.05 | I58: =+E57-E10 -> 4417849 | J58: =+H58/I58 -> 0.16106075
B59: Insurance | D59: 154384 | E59: =ROUND(SUM(E57:E58)*RFE!F21,0) -> 128235 | F59: -20900 | H59: GRs + GCs | I59: trade w/out GRs | J59: %
B60: Fee | D60: 221540 | E60: =ROUND(SUM(E57:E59)*RFE!F22,0) -> 170873 | F60: =+E60-D60 -> -50667
B61: TOTAL | D61: 6551268.2 | E61: =SUM(E57:E60) -> 5428499.1 | F61: =+E61-D61 -> -1122769.2 | I61: =SUM(E58:E60) -> 645850.05
I62: =I61/E57 -> 0.13504024
B63: Alternate 1
B64: Furnish and install Hidden Stringer Steel staircase BUDGET
B65: Metal work | C65: 173400
B66: Glass Railing | C66: 125000
B67: Wood treads and risers | C67: 50000
B68: Sub-Total Construction Costs | E68: =SUM(C65:C68) -> 348400
B69: General Conditions | E69: =SUM(E68)*RFE!$F$20 -> 25259
B70: Insurance | E70: =SUM(E68:E69)*RFE!$F$21 -> 9341.475
B71: Fee | E71: =SUM(E68:E70)*RFE!$F$22 -> 12447.515
B72: TOTAL | E72: =SUM(E68:E71) -> 395447.99
B74: Alternate 2
B75: Furnish and install Window walls at Rear of Building by GoldBreht
B76: Sub-Total Construction Costs | E76: =+'Bid Comparison '!J34 -> 366200
B77: General Conditions | E77: =SUM(E76)*RFE!$F$20 -> 26549.5
B78: Insurance | E78: =SUM(E76:E77)*RFE!$F$21 -> 9818.7375
B79: Fee | E79: =SUM(E76:E78)*RFE!$F$22 -> 13083.468
B80: TOTAL | E80: =SUM(E76:E79) -> 415651.71
B82: Alternate 3
B83: Rasomuro Interior Door Systems by Lauldi, including Installation
B84: Sub-Total Construction Costs | E84: =187000+9000 -> 196000
B85: General Conditions | E85: =SUM(E84)*RFE!$F$20 -> 14210
B86: Insurance | E86: =SUM(E84:E85)*RFE!$F$21 -> 5255.25
B87: Fee | E87: =SUM(E84:E86)*RFE!$F$22 -> 7002.6206
B88: TOTAL | E88: =SUM(E84:E87) -> 222467.87
B90: Alternate 4
B91: =+Estimate!C455 -> Specialty Glass work at cellar and bathrooms
B92: Glass walls at sauna & steam rooms w/doors (Bendheim allowance $75/SF)
B93: Glass walls & door at cellar bathroom (Bendheim Allowance $75/SF)
B94: Bendheim glass panels at walls and ceiling of the elevator cab
B95: Glass walls/doors at WC and shower at Primary Bathroom w/ doors
B96: Shower enclosure at Guest Bath
B97: Shower Panels at 3rd level bathrooms
B98: Glass wall from 1st to 2nd floor at staircase
B99: Distraction film at glass walls
B100: Glass railings at Livingroom & Primary suite
B101: Sub-Total Construction Costs | E101: =+Estimate!H465 -> 150700
B102: General Conditions | E102: =SUM(E101)*RFE!$F$20 -> 10925.75
B103: Insurance | E103: =SUM(E101:E102)*RFE!$F$21 -> 4040.6438
B104: Fee | E104: =SUM(E101:E103)*RFE!$F$22 -> 5384.1578
B105: TOTAL | E105: =SUM(E101:E104) -> 171050.55
B107: Alternate 5
B108: Wood Roof Decks Allowances
...

Sheet VE
A3: =Estimate!C2 -> Town House Renovation
A4: =Estimate!C3 -> 60 Bank Street
A5: =Estimate!C4 -> New York, NY 10014
A6: =CONCATENATE("Proposal #",RFE!E14) -> Proposal #24-038C
A7: Value Engineering Suggestions
A9: No. | B9: VE Item | C9: Specific Substitution / Product
A10: 1 | B10: SOE | C10: Possible alternate SOE procedures to be reviewed between SOE contractor and EOR
A11: 2 | B11: Wall Finishes | C11: Paint vs, Plaster at 3rd floor finishes (all paint as level 5)
A12: 3 | B12: Wood Flooring | C12: Specified flooring is very expensive- review alternate options
A13: 4 | B13: Interior Doors | C13: Replace Rasomuro Interior Door Systems with local equivalent with shop finishes
A14: 5 | B14: Hardware | C14: Replace Valli & Valli or FSB with Emtek “Stretto” or “Select” levers in satin brass
A15: 6 | B15: Casework in Secondary Spaces | C15: Use Reform “Basis” or Henrybuilt “Standard Series” in offices, laundry, and secondary baths
A16: 7 | B16: Windows | C16: Replace Specialty Windows at rear with local tile and turn windows with similar finish and profile
A17: 8 | B17: Mirror Systems | C17: Replace custom light-integrated mirrors with Electric Mirror “Integrity” or Robern “AI Series” —
A18: 9 | B18: Millwork Veneers | C18: Source Millwork veneers locally and fabricate in US
A19: 10 | B19: Radiant Flooring | C19: Reduce scope by deleting at wood flooring areas at 3rd floor, roof and other zones
A20: 11 | B20: Starcase & Handrails | C20: Source the staircase locally including the handrails
A21: 12 | B21: Tile Format & Pattern | C21: Instead of herringbone or chevron in marble, use 24x48” porcelain tiles (Stone Source or Artistic Tile) in stacked pattern
... A33: 24 | B33: Fireplace Surrounds | C33: Swap marble or limestone mantels with Chesneys “Classic Collection” cast stone or Eldorado Architectural Stone kits — prefab and site-trimmable.

Sheet Drawing Manifest
A2: Job Name
A3: Street Address
A4: Town or Boro, State, Zip
A5: =CONCATENATE(RFE!C11, " Floor") -> Floor
A6: =CONCATENATE("Proposal #",RFE!E14) -> Proposal #24-038C
A8: Drawing Manifest
A10: REF | B10: Description | C10: Date | D10: A/E

Sheet Notes & Clarifications
A3: =Estimate!C2 -> Town House Renovation
A4: =Estimate!C3 -> 60 Bank Street
A5: =Estimate!C4 -> New York, NY 10014
A6: =CONCATENATE(RFE!C11, " Floor") -> Floor
A7: =CONCATENATE("Proposal #",RFE!E14) -> Proposal #24-038C
B10: NOTES AND CLARIFICATIONS
A11: 1 | B11: Building utility, shutdown, tie-in, and/or elevator charges are to be paid by others.
A12: 2 | B12: All Building Department fees and filing charges are by others. Cost to pick-up permit is included.
A13: 3 | B13: System furniture, including delivery, handling, installation or clean-up are excluded. Installation of electrical device are included.
A14: 4 | B14: Furnishing, installing and setting of file cabinets, etc., are excluded.
A15: 5 | B15: Removal of asbestos, lead paint, PCB ballasts, and/or replacement of equivalent material including any associated air monitoring/hygienist costs is not included.
A16: 6 | B16: Overtime, except for demolition and building rules/regulations, is not included.
A17: 7 | B17: Telephone and data cabling is not included.
A18: 8 | B18: Fire watch, temporary sprinkler loop, and/or daily activation of the system is not included.
A19: 9 | B19: After hour permits are excluded.
A20: 10 | B20: All work and associated costs for Local #1 and #14, and hoisting is not included.
A21: 11 | B21: Removal of vinyl floor tile which may exist under carpeting is excluded.
A22: 12 | B22: Work at existing induction units is not included, unless specifically shown on drawings.
... A30: 20 | B30: Final payment shall not be withheld due to fire alarm inspections and signoff or due to BEC signoff which is beyond our control.
B32: SPECIFIC NOTES AND CLARIFICATIONS
A33: 1 | B33: We included the rear window elevations to be by Goldbrecht
A34: 2 | B34: Bath Vanities including integral sinks are the be furnished by Others
A35: 3 | B35: Mirror panels at Master suite Wardrobe room are assumed to be by the Owners Millworker.
A36: 4 | B36: We have included the "Stone Tile" through out at an allowance of $90/SF (with Exception of the M Bathroom which we allowed $110/SF)and assume it will be cut to size before shipping. Porcelain tile for the staff bath was included at $50/SF.
A37: 5 | B37: We have include the Bendheim glass materials @ $75/SF
A38: 6 | B38: We have not included installation of the window shutters at the front of the building
A39: 7 | B39: We have assumed that the locksets and handles or levers for the wood doors will be furnished by the Owner.
A40: 8
A41: 9
A42: 10
A43: 11
A44: 12
B47: =+RFE!B46 -> 0

Sheet Estimate
C2: =RFE!C8 -> Town House Renovation | G2: Proposal # : | H2: =RFE!$E$14 -> 24-038C
C3: =RFE!C9 -> 60 Bank Street | E3: Rev. | F3: 45897 | G3: Revised | H3: 45965
C4: =RFE!C10 -> New York, NY 10014
A6: CSI
A7: DIVISION | B7: TRADE: | C7: ITEM DESCRIPTION | D7: QTY | E7: UNT | F7: COST/PER | G7: SUBTOTAL | H7: TOTAL
A9: 1050 | B9: General Requirements
C10: Super | D10: 60 | E10: wk. | F10: 3300 | G10: =ROUND(SUM(D10)*F10,0) -> 198000
C11: Labor Foreman | D11: 40 | E11: wk. | F11: 1950 | G11: =ROUND(SUM(D11)*F11,0) -> 78000
C12: Laborers (part time) | D12: 40 | E12: wk. | F12: 1000 | G12: =ROUND(SUM(D12)*F12,0) -> 40000
C13: Containers | D13: 40 | E13: wk. | F13: 1220 | G13: =ROUND(SUM(D13)*F13,0) -> 48800
C14: Misc. Demo and Carting | D14: 1 | E14: LS
H15: =SUM(G9:G15) -> 364800
A17: 1100 | B17: Protection & Logistics
C18: Install crack & movement monitors and survey weekly during structural work | D18: 1 | E18: Allow | F18: 20000 | G18: =ROUND(SUM(D18)*F18,0) -> 20000
C19: Temporary staircases | D19: 5 | E19: Flrs | F19: 3000 | G19: =ROUND(SUM(D19)*F19,0) -> 15000
C20: OSHA railing and fall protection | D20: 1 | E20: LS
C21: Bridge & scaffold at street aide during Facade & Cornice work | D21: 1 | E21: LS | F21: 20000 | G21: =ROUND(SUM(D21)*F21,0) -> 20000
C22: Dust & Noise mitigation | D22: 1 | E22: LS | F22: 12000 | G22: =ROUND(SUM(D22)*F22,0) -> 12000
C23: Site Safety & Logistic plan | D23: 1 | E23: LS | F23: 25000 | G23: =ROUND(SUM(D23)*F23,0) -> 25000
C24: Rigging for Roof top equipment and materials | D24: 1 | E24: LS | F24: 30000 | G24: =ROUND(SUM(D24)*F24,0) -> 30000
H25: =SUM(G17:G25) -> 122000
A27: 2000 | B27: Excavation/Foundation
G28: =ROUND(SUM(D28)*F28,0) -> 0
C29: Excavation
C30: Demo Cellar Slab | D30: 1 | E30: LS | F30: 50000 | G30: =+F30*D30 -> 50000
C31: Excavation and backfill | D31: 1 | E31: LS | F31: 300000 | G31: =+F31 -> 300000
C32: export excavated soil | D32: 1 | E32: LS | G32: Included
C33: Foundations & Slabs below grade | G33: =ROUND(SUM(D33)*F33,0) -> 0
C34: Basement 10" slab (includes extension) | D34: 1 | E34: LS | F34: 75000 | G34: 75000
C35: Areaway slab and steps | D35: 1 | E35: LS | G35: Included
C36: Waterproofing below grade and behind foundation walls including rigid insulation | D36: 1 | E36: LS | F36: 95000 | G36: =ROUND(SUM(D36)*F36,0) -> 95000
C37: Wall footings & Foundation walls | D37: 1 | E37: LS | F37: 125000 | G37: 125000
H38: =SUM(G27:G38) -> 645000
A40: 2010 | B40: Underpinning, Shoring & Support of Excavation
C41: Shore rear corners while removing rear wall | D41: 1 | E41: LS | G41: 420000
C42: Underpinning at west wall for elevator pit and lowered slab areas | D42: 1 | E42: LS | G42: Included
C43: Provide vertical channels to be moved up the walls as each floor is set in place and the next is ready for demo | D43: 1 | E43: LS | G43: Included
C44: Bracing and jacks for each under pinning lift (moved as the adjacent lifts are set) | D44: 1 | E44: LS | G44: Included
C45: F&I Soldier piles and wood timber lagging | D45: 1 | E45: LS | G45: Included
C46: Include all steel bracing, whalers and Rakers, including welded connections | D46: 1 | E46: LS | G46: Included
C47: Concrete heel blocks | D47: 1 | E47: LS | G47: Included
C48: Parge rubble walls | D48: 1 | E48: LS | G48: Included
H49: =SUM(G40:G49) -> 420000
A51: 2050 | B51: Demolition
C53: Removal of floor joists at the parlor level and those from the south side of the new elevator shaft to the northside of the new stair case | D53: 2600 | E53: SF | F53: 25 | G53: =ROUND(SUM(D53)*F53,0) -> 65000
C54: Remove rear wall | D54: 1000 | E54: SF | F54: 55 | G54: =ROUND(SUM(D54)*F54,0) -> 55000
C55: Remove roofing prior to roof deck demo - (assuming ACM has been removed by others) | D55: 1000 | E55: SF | F55: 10 | G55: =ROUND(SUM(D55)*F55,0) -> 10000
C56: Remove windows and provide removable insulated panels | D56: 10 | E56: EA | F56: 500 | G56: =ROUND(SUM(D56)*F56,0) -> 5000
C57: Create new opening for entry doors | D57: 2 | E57: LS | F57: 3000 | G57: =ROUND(SUM(D57)*F57,0) -> 6000
C58: Remove brick arch walls in cellar | D58: =30*10 -> 300 | E58: SF | F58: 20 | G58: =ROUND(SUM(D58)*F58,0) -> 6000
C59: Remove plaster from staircase wall | D59: 920 | E59: SF | F59: 15 | G59: =ROUND(SUM(D59)*F59,0) -> 13800
C60: Remove staircase and related framing | D60: 5 | E60: Flrs | F60: 3500 | G60: =ROUND(SUM(D60)*F60,0) -> 17500
H62: =SUM(G51:G62) -> 178300
A64: 2090 | B64: Asbestos Removal
H65: Not Included
A68: 2100 | B68: Site Work
C70: Blue Stone at areaway including treads | D70: 140 | E70: SF | F70: 150 | G70: =+F70*D70 -> 21000
C71: Brick or Stone pavers at rear garden | D71: 355 | E71: SF | F71: 75 | G71: =+F71*D71 -> 26625
C72: New sidewalk | D72: 200 | E72: SF | F72: 25 | G72: =+F72*D72 -> 5000
C73: New Curb | D73: 22 | E73: LF | F73: 75 | G73: =+F73*D73 -> 1650
C74: New Tree pit, frame and grille | D74: 1 | E74: LS | F74: 15000 | G74: =+F74*D74 -> 15000
C75: New 6" tree | D75: 1 | E75: LS | F75: 7500 | G75: =+F75*D75 -> 7500
H76: =SUM(G68:G76) -> 76775
A78: 3000 | B78: Concrete
C80: Concrete on metal deck at the parlor level & Bulkhead | D80: 1300 | E80: SF | F80: 20 | G80: =ROUND(SUM(D80)*F80,0) -> 26000
H81: =SUM(G78:G81) -> 26000
A83: 4000 | B83: Masonry
C84: CMU shaft wall on 3 sides for the elevator, grout filled with bond beam reinforcement at all floors | D84: =60*20 -> 1200 | E84: SF | F84: 30 | G84: =ROUND(SUM(D84)*F84,0) -> 36000
C85: Loose lintels for door openings | D85: 5 | E85: EA | F85: 500 | G85: =ROUND(SUM(D85)*F85,0) -> 2500
C86: Brick return and entry at new main entry doors | D86: 1 | E86: LS | F86: 5000 | G86: =ROUND(SUM(D86)*F86,0) -> 5000
C87: Block and Brick at Roof Bulkhead | D87: 450 | E87: SF | F87: 45 | G87: =ROUND(SUM(D87)*F87,0) -> 20250
C88: Interior Masonry Remediation
C89: Remove and rebuild bulging are of 3rd floor west wall, including shoring the joist above while the work is completed | D89: 150 | E89: SF | F89: 60 | G89: =ROUND(SUM(D89)*F89,0) -> 9000
C90: Misc. patching at party walls and rear corners | D90: 1 | E90: allow | F90: 5000 | G90: =ROUND(SUM(D90)*F90,0) -> 5000
C91: Infill exterior wall areas with brick | D91: 400 | E91: SF | F91: 35 | G91: =ROUND(SUM(D91)*F91,0) -> 14000
C92: Remove wood nailers, point and patch brick walls throughout east & west walls | D92: 2800 | E92: SF | F92: 7 | G92: =ROUND(SUM(D92)*F92,0) -> 19600
C93: Remove wood nailers and point front wall interior | D93: 1 | E93: LS | F93: 10000 | G93: =ROUND(SUM(D93)*F93,0) -> 10000
C94: Provide ties and straps to front wall for carpenter to connect to new joist "sisters" | D94: 1 | E94: LS | F94: 20000 | G94: =ROUND(SUM(D94)*F94,0) -> 20000 | I94: =SUM(G89:G94) -> 77600
H95: =SUM(G83:G95) -> 141350
A97: 4500 | B97: Front Façade
C98: Point & repair brick | D98: =850-60-75-70-25 -> 620 | E98: SF | F98: 20 | G98: =ROUND(SUM(D98)*F98,0) -> 12400
C99: Touch up headers and sills at existing windows | D99: 10 | E99: EA | F99: 500 | G99: =ROUND(SUM(D99)*F99,0) -> 5000
C100: Touch up brownstone finish below 1st floor | D100: 110 | E100: SF | F100: 25 | G100: =ROUND(SUM(D100)*F100,0) -> 2750
C101: Finish over New Stairs to 1st floor in Brownstone finish | D101: 1 | E101: LS | F101: 15000 | G101: =ROUND(SUM(D101)*F101,0) -> 15000
C102: Entry Door Surround and pediment | D102: 1 | E102: LS | F102: 20000 | G102: =ROUND(SUM(D102)*F102,0) -> 20000
C103: Fiber glass cornice and copper cap | D103: 23 | E103: Allow/LF | F103: 75 | G103: =ROUND(SUM(D103)*F103,0) -> 1725
C104: Lower window sills at the parlor level windows and redo sill details | D104: 2 | E104: EA | F104: 5000 | G104: =ROUND(SUM(D104)*F104,0) -> 10000
H105: =SUM(G97:G105) -> 66875
A107: 5120 | B107: Structural Steel
C108: Steel columns for rear steel beams | D108: 200 | E108: LF | F108: 425 | G108: =ROUND(SUM(D108)*F108,0) -> 85000
C109: Steel beams to support slab edges and window walls | D109: 300 | E109: LF | F109: 200 | G109: =ROUND(SUM(D109)*F109,0) -> 60000
C110: Steel and metal deck for parlor level floor & roof bulkhead | D110: 1300 | E110: SF | F110: 45 | G110: =ROUND(SUM(D110)*F110,0) -> 58500
C111: Dunnage for AC equipment | D111: 1 | E111: LS | F111: 5000 | G111: =ROUND(SUM(D111)*F111,0) -> 5000
C112: Steel phased erection (floor by floor) | D112: 1 | E112: LS | F112: 30000 | G112: =ROUND(SUM(D112)*F112,0) -> 30000
H113: =SUM(G107:G113) -> 238500
A115: 5400 | B115: Ornamental Iron Works
C116: Wrought Iron Railings at Entry to basement level and at grade | D116: 1 | E116: LS | F116: 20000 | G116: =ROUND(SUM(D116)*F116,0) -> 20000
C117: Wrought Iron Handrails at new entry staircase | D117: 1 | E117: LS | F117: 20000 | G117: =ROUND(SUM(D117)*F117,0) -> 20000
C118: Wrought Iron Basement level Gate | D118: 1 | E118: LS | F118: 10500 | G118: =ROUND(SUM(D118)*F118,0) -> 10500
C119: WI Wall rails to Basement entry | D119: 2 | E119: EA | F119: 2000 | G119: =ROUND(SUM(D119)*F119,0) -> 4000
...

Sheet Sheet1

Sheet General Conditions
C2: =Estimate!C2 -> Town House Renovation | F2: Proposal # : | G2: =RFE!$E$14 -> 24-038C
C3: =Estimate!C3 -> 60 Bank Street | F3: Date : | G3: =RFE!$F$3 -> 0
C4: =Estimate!C4 -> New York, NY 10014 | F4: Revised Date : | G4: =TODAY() -> 45965
C5: =Estimate!#REF! -> #REF! | F5: Estimator : | G5: =RFE!$E$8 -> 0
A9: Trade: | C9: Item Description: | D9: Qty | E9: Unt | F9: Cst/per | G9: Sub-Total | H9: Total
B10: General Conditions
B11: - | C11: Days
C12: Labor | E12: Dys | F12: =56*7 -> 392 | G12: =ROUND(SUM(D12)*F12,0) -> 0
C13: Supervisor | E13: Dys | F13: =8*70 -> 560 | G13: =ROUND(SUM(D13)*F13,0) -> 0
B14: - | C14: Weeks
C15: Labor | E15: Wks | F15: =+F12*5 -> 1960 | G15: =ROUND(SUM(D15)*F15,0) -> 0
C16: Supervisor | E16: Wks | F16: =+F13*5 -> 2800 | G16: =ROUND(SUM(D16)*F16,0) -> 0
B17: Direct Project Costs - Over GC's
B18: - | C18: Manpower:
C19: Project Manager | E19: Dys | F19: =85*8 -> 680 | G19: =ROUND(SUM(D19)*F19,0) -> 0 | J19: =365/8 -> 45.625
C20: Supervisor | E20: Dys | F20: 560 | G20: =ROUND(SUM(D20)*F20,0) -> 0
C21: Laborer | E21: Dys | F21: =+F12 -> 392 | G21: =ROUND(SUM(D21)*F21,0) -> 0
C22: Overtime allowance (premium) | E22: Hr | F22: 25 | G22: =ROUND(SUM(D22)*F22,0) -> 0
B23: - | C23: Protection Items:
C24: Green dust | E24: Ea | F24: 48 | G24: =ROUND(SUM(D24)*F24,0) -> 0
C25: Masonite | E25: Ea | F25: 20 | G25: =ROUND(SUM(D25)*F25,0) -> 0
C26: Plastic | E26: Roll | F26: 25 | G26: =ROUND(SUM(D26)*F26,0) -> 0
C27: Paper | E27: Roll | F27: 55 | G27: =ROUND(SUM(D27)*F27,0) -> 0
C28: Duct tape | E28: Roll | F28: 8.5 | G28: =ROUND(SUM(D28)*F28,0) -> 0
C29: Masking tape | E29: Roll | F29: 3.25 | G29: =ROUND(SUM(D29)*F29,0) -> 0
B30: - | C30: Rubbish Removals:
C31: Mini containers | E31: Ea | F31: 23 | G31: =ROUND(SUM(D31)*F31,0) -> 0
C32: Roll - off container - 40 yd.. | E32: Ea | F32: 1200 | G32: =ROUND(SUM(D32)*F32,0) -> 0
B33: - | C33: Misc. Items
C34: On - site telephone | E34: Wks | F34: 250 | G34: =ROUND(SUM(D34)*F34,0) -> 0
C35: Blueprints | E35: Ea | F35: 1.75 | G35: =ROUND(SUM(D35)*F35,0) -> 0
C36: Travel costs (allowance) | E36: LS | F36: 500 | G36: =ROUND(SUM(D36)*F36,0) -> 0
C37: Misc. allowances | E37: LS | F37: 1500 | G37: =ROUND(SUM(D37)*F37,0) -> 0 | H37: =SUM(G17:G37) -> 0

Sheet Bid Comparison 
A4: =Estimate!C2 -> Town House Renovation | D4: DUE For Subs | E4: =+RFE!E44 -> date? | H4: BID REVIEW - SUBCONTRACTOR ANALYSIS SPREADSHEET
A5: =Estimate!C3 -> 60 Bank Street
A6: =Estimate!C4 -> New York, NY 10014 | H6: COMPETITION:
A7: =Estimate!#REF! -> #REF! | C7: PROPOSAL #: | E7: =TODAY() -> 45965 | G7: =+RFE!E14 -> 24-038C
C8: Estimated | D8: Proposed | E8: REVIEWED | F8: 7% Discount | G8: LOW
A9: ITEM | B9: TRADE DESCRIPTION | C9: Amount | D9: Amount | E9: PRICE | F9: to low bid | G9: BID | H9: SUB #1 | I9: BID | J9: SUB #2 | K9: BID | L9: SUB #3 | M9: BID | N9: SUB #4 | O9: BID | P9: SUB #5 | Q9: BID | R9: SUB #6 | S9: BID
A10: 1050 | B10: General Requirements | C10: =Estimate!H15 -> 364800 | E10: =+C10 -> 364800 | F10: =G10*0.93 -> 0 | G10: =MIN(H10:S10) -> 0
A11: 1100 | B11: Protection & Logistics | C11: =+Estimate!H25 -> 122000 | E11: =+C11 -> 122000
A12: 2000 | B12: Excavation/Foundation | C12: =+Estimate!H38-C14 -> 550000 | E12: =+C12 -> 550000 | F12: =G12*0.93 -> 269514 | G12: =MIN(H12:S12) -> 289800 | H12: Skylight | I12: 289800 | J12: Centrifical | K12: =260774+61985+126358+137252 -> 586369 | L12: C&M | M12: 1100000
A13: 2010 | B13: Underpinning, Shoring & Support of Excavation | C13: =+Estimate!H49 -> 420000 | E13: =+C13 -> 420000 | H13: Skylight | I13: 891300 | K13: 460393
B14: Waterproofing | C14: =+Estimate!G36 -> 95000 | E14: =+C14 -> 95000 | H14: Skylight | I14: 95800 | K14: 99130
A15: 2050 | B15: Demolition | C15: =+Estimate!H62 -> 178300 | E15: =+C15 -> 178300 | F15: =G15*0.93 -> 254820 | G15: =MIN(H15:S15) -> 274000 | H15: Jato | I15: 274000 | J15: =SUM(I12:I14) -> 1276900 | L15: =SUM(K12:K14) -> 1145892
A16: 2090 | B16: Asbestos Removal | C16: =+Estimate!H65 -> Not Included | E16: =+C16 -> Not Included | F16: =G16*0.93 -> 0 | G16: =MIN(H16:S16) -> 0
A17: 2100 | B17: Site Work | C17: =+Estimate!H76 -> 76775 | E17: =+C17 -> 76775
A18: 3000 | B18: Concrete | C18: =+Estimate!H81 -> 26000 | E18: =+C18 -> 26000 | F18: =G18*0.93 -> 0 | G18: =MIN(H18:S18) -> 0 | J18: Centrifical | K18: on deck in styeel#
A19: 4000 | B19: Masonry | C19: =+Estimate!H95 -> 141350 | E19: =+C19 -> 141350 | F19: =G19*0.93 -> 0 | G19: =MIN(H19:S19) -> 0
A20: 4500 | B20: Masonry Restoration | C20: =+Estimate!H105 -> 66875 | E20: =+C20 -> 66875 | F20: =G20*0.93 -> 0 | G20: =MIN(H20:S20) -> 0
A21: 5120 | B21: Structural Steel | C21: =+Estimate!H113 -> 238500 | E21: =+C21 -> 238500 | F21: =G21*0.93 -> 207991.71 | G21: =MIN(H21:S21) -> 223647 | H21: Handco | I21: 284800 | J21: NC | K21: 317975 | L21: King C | M21: 285000 | N21: Bronx IW | O21: 223647 | P21: Centrifical | Q21: 310707 | R21: Maspeth | S21: 326780
A22: 5400 | B22: Ornamental Iron Works | C22: =+Estimate!H123 -> 70750 | E22: =+C22 -> 70750 | H22: Handco | I22: 219375 | L22: King C | M22: Included
A23: 5500 | B23: Miscellaneous Iron | C23: =+Estimate!H128 -> 24800 | E23: =+C23 -> 24800 | F23: =G23*0.93 -> 0 | G23: =MIN(H23:S23) -> 0 | H23: Handco | I23: Included
A24: 6400 | B24: Architectural Woodwork | C24: =+Estimate!H146 -> 54350 | E24: =+C24 -> 54350 | F24: =G24*0.93 -> 0 | G24: =MIN(H24:S24) -> 0
A25: =+Estimate!A147 -> 6500 | B25: Rough Carpentry | C25: =+Estimate!H158-C26 -> 238060 | E25: =+Estimate!H158-E26 -> 238060 | H25: swift | I25: 267000
B26: Finish Carpentry | C26: =SUM(Estimate!G154:G157) -> 25000 | E26: =SUM(Estimate!G154:G157) -> 25000
A27: 7500 | B27: Roofing/Waterproofing | C27: =+Estimate!H165 -> 45975 | E27: =+C27 -> 45975 | F27: =G27*0.93 -> 0 | G27: =MIN(H27:S27) -> 0
A28: 8110 | B28: Doors, Frames & Hardware | C28: =+Estimate!H180 -> See Alternate | E28: =+C28 -> See Alternate | F28: =G28*0.93 -> 122351.73 | G28: =MIN(H28:S28) -> 131561 | H28: Lualdi (Interior doors only) | I28: 131561
B29: Finish Hardware (Locksets & Levers | C29: By Others | E29: =+C29 -> By Others
A30: 8520 | B30: =+Estimate!B182 -> Wood Windows | C30: =+Estimate!H184 -> 45000 | E30: =+C30 -> 45000 | F30: =G30*0.93 -> 0 | G30: =MIN(H30:S30) -> 0
A31: 8800 | B31: Architectural Metal & Glass | C31: =+Estimate!H189 -> 12200 | E31: =+C31 -> 12200 | F31: =G31*0.93 -> 0 | G31: =MIN(H31:S31) -> 0
A32: 8810 | B32: Window Film | C32: =+Estimate!H192 -> Alternate | E32: =+C32 -> Alternate | F32: =G32*0.93 -> 0 | G32: =MIN(H32:S32) -> 0
A33: 8900 | B33: =+Estimate!B194 -> Window Walls | C33: =+Estimate!H199 -> Alternate | E33: =+C33 -> Alternate | F33: =G33*0.93 -> 275410.2 | G33: =MIN(H33:S33) -> 296140 | H33: Goldbrecht | I33: =(197580+18300+4700+10100+7170+31180+1700+1270)*1.08875 -> 296140
B34: Installation | E34: Included | I34: =46650+10030+13380 -> 70060 | J34: =SUM(I33:I34) -> 366200
A35: 9250 | B35: Drywall & Carpentry | C35: =+Estimate!H212 -> 214976 | E35: =+C35 -> 214976 | F35: =G35*0.93 -> 189720 | G35: =MIN(H35:S35) -> 204000 | H35: swift | I35: 204000
A36: 9300 | B36: Ceramic Tile/Stone | C36: =+Estimate!H228 -> 67075 | E36: =+C36 -> 67075 | F36: =G36*0.93 -> 0 | G36: =MIN(H36:S36) -> 0
A37: 9550 | B37: Wood Flooring | C37: =+Estimate!H233 -> 116853 | E37: =+C37 -> 116853 | F37: =G37*0.93 -> 109838.58 | G37: =MIN(H37:S37) -> 118106 | H37: Heywood-Berk | I37: =108968+9138 -> 118106
B38: Specialty Finishes | C38: =+Estimate!H240 -> 55610 | E38: =+C38 -> 55610 | H38: Conkreto | I38: 55983
B39: Artisan Plaster | C39: =+Estimate!H246 -> 120650 | E39: =+C39 -> 120650
A40: 9900 | B40: Painting | C40: =+Estimate!H253 -> 45000 | E40: =+C40 -> 45000 | F40: =G40*0.93 -> 0 | G40: =MIN(H40:S40) -> 0
A41: 10800 | B41: Toilet Accessories | C41: =+Estimate!H256 -> Furnished by others | E41: =+C41 -> Furnished by others | F41: =G41*0.93 -> 0 | G41: =MIN(H41:S41) -> 0
A42: 11450 | B42: Appliances | C42: =+Estimate!#REF! -> #REF! | E42: =+C42 -> #REF! | F42: =G42*0.93 -> 0 | G42: =MIN(H42:S42) -> 0
A43: =+Estimate!A258 -> 11750 | B43: =+Estimate!B258 -> Fireplace | C43: =+Estimate!H259 -> Alternate | E43: =+C43 -> Alternate
A44: 12500 | B44: Window Treatment | C44: By Others | D44: Allowances | E44: =+C44 -> By Others | F44: =G44*0.93 -> 0 | G44: =MIN(H44:S44) -> 0
A45: =+Estimate!A264 -> 13750 | B45: =+Estimate!B264 -> Sauna and Steam Room | C45: =+Estimate!H265 -> By Owner | E45: By Others
A46: 14200 | B46: Elevator Work | C46: =+Estimate!H270 -> 124750 | E46: =+C46 -> 124750 | F46: =G46*0.93 -> 110205 | G46: =MIN(H46:S46) -> 118500 | H46: Mobility | I46: 118500
A47: 15400 | B47: Plumbing | C47: =+Estimate!H318 -> 315000 | E47: =+C47 -> 315000 | F47: =G47*0.93 -> 311550 | G47: =MIN(H47:S47) -> 335000 | H47: Donato | I47: 335000
A48: 15450 | B48: Plumbing Fixtures | C48: =Estimate!H321 -> Furnished By the Owner | E48: =+C48 -> Furnished By the Owner | F48: =G48*0.93 -> 0
A49: 15500 | B49: Sprinklers | C49: =+Estimate!H330 -> 70400 | E49: =+C49 -> 70400 | F49: =G49*0.93 -> 71052 | G49: =MIN(H49:S49) -> 76400 | H49: Capitol | I49: 76400
A50: 15600 | B50: HVAC | C50: =+Estimate!H344 -> 495000 | E50: =+C50 -> 495000 | F50: =G50*0.93 -> 474300 | G50: =MIN(H50:S50) -> 510000 | H50: Ulocn | I50: 510000 | J50: Comfortaire
A51: 16000 | B51: Electric | C51: =+Estimate!H405-C52 -> 192900 | E51: =+C51 -> 192900 | F51: =G51*0.93 -> 183005.4 | G51: =MIN(H51:S51) -> 196780 | H51: M&T | I51: 294000 | J51: Echo | K51: 359241 | L51: Ostroff | M51: =418000-M52+M54 -> 274300 | N51: Ennell | O51: 196780
B52: Electric Radiant Heat | C52: 168700 | E52: 168700 | I52: Not Incld | K52: Included | M52: 168700
B53: Install Controls | E53: Included | K53: Included | M53: Included
B54: Millwork lighting | E54: Included | K54: TBD | M54: 25000
B55: POE sleeves | E55: Included | K55: TBD
A56: 16300 | B56: Communications Cabling | C56: =+Estimate!H408 -> By Others | E56: =+C56 -> By Others | F56: =G56*0.93 -> 0 | G56: =MIN(H56:S56) -> 0
A57: 16500 | B57: Light Fixtures | C57: =+Estimate!H411 -> By Others | E57: =+C57 -> By Others | F57: =G57*0.93 -> 0 | G57: =MIN(H57:S57) -> 0
A58: 17300 | B58: Security Systems | C58: =+Estimate!H414 -> By Others | E58: =+C58 -> By Others | F58: =G58*0.93 -> 0 | G58: =MIN(H58:S58) -> 0
A59: 00000 | B59: Final Cleaning | C59: =+Estimate!#REF! -> #REF! | E59: =+C59 -> #REF! | F59: =G59*0.93 -> 0 | G59: =MIN(H59:S59) -> 0
B61: SUB-TOTAL | C61: =SUM(C10:C60) -> #REF! | D61: =+Estimate!H416 -> 4782649 | E61: =SUM(E10:E60) -> #REF! | F61: =SUM(F10:F60) -> 2579758.6 | G61: =+D61-E61 -> #REF! | H61: ITALICS = BID NEEDS REVIEW
B62: GENERAL CONDITIONS | E62: =SUM(E61:E61)*RFE!$F$20 -> #REF! | F62: =SUM(F61:F61)*RFE!$F$20 -> 187032.5 | G62: =+RFE!F20 -> 0.0725 | H62: =+E61-E10 -> #REF! | I62: =+E62+E10 -> #REF! | J62: =+I62/H62 -> #REF!
B63: INSURANCE | E63: =SUM(E61:E62)*RFE!$F$21 -> #REF! | F63: =SUM(F61:F62)*RFE!$F$21 -> 69169.778 | G63: =+RFE!F21 -> 0.025 | H63: tgrade sm w/o GRs | I63: GRs + GCs
B64: FEE | E64: =SUM(E61:E63)*RFE!$F$22 -> #REF! | F64: =SUM(F61:F63)*RFE!$F$22 -> 92168.729 | G64: =+RFE!F22 -> 0.0325
B65: TOTAL | E65: =SUM(E61:E64) -> #REF! | F65: =SUM(F61:F64) -> 2928129.6
B69: Alternate 1
B70: Furnish and install Hidded Stringer Steel staircase
B71: Metal work | F71: =G71*0.93 -> 161262 | G71: =MIN(I71,K71,M71,Q71) -> 173400 | H71: Handco | I71: 173400 | J71: King C | K71: 178500
B72: Glass Railing | C72: 10000 | D72: Allow | F72: =G72*0.93 -> 69750 | G72: 75000 | K72: Included
B73: Wood treads and risers | C73: 500 | D73: Allow | F73: =G73*0.93 -> 32550 | G73: 35000
B74: trade | F74: =G74*0.93 -> 0 | G74: =MIN(I74,K74,M74,Q74) -> 0
B75: SUB-TOTAL | C75: =Estimate!#REF! -> #REF! | E75: =SUM(E70:E74) -> 0
B76: GENERAL CONDITIONS | C76: =C75*RFE!$F$20 -> #REF! | E76: =E75*RFE!$F$20 -> 0 | G76: =SUM(G69:G74)*RFE!$F$20 -> 20546.5
B77: INSURANCE | C77: =SUM(A69:A76)*RFE!$F$21 -> 0 | E77: =SUM(C69:C76)*RFE!$F$21 -> #REF! | G77: =SUM(G69:G76)*RFE!$F$21 -> 7598.6625
B78: FEE | C78: =SUM(A69:A77)*RFE!$F$22 -> 0 | E78: =SUM(C69:C77)*RFE!$F$22 -> #REF! | G78: =SUM(G69:G77)*RFE!$F$22 -> 10125.218
B79: TOTAL | C79: =SUM(C75:C78) -> #REF! | E79: =SUM(E75:E78) -> #REF! | G79: =SUM(G69:G78) -> 321670.38
B81: Alternate 2
B82: Gym Towel Station
B83: trade | F83: =G83*0.93 -> 21948 | G83: =MIN(I83,K83,M83,Q83) -> 23600 | H83: Handco | I83: 23600
B84: trade | F84: =G84*0.93 -> 0 | G84: =MIN(I84,K84,M84,Q84) -> 0
B85: trade | F85: =G85*0.93 -> 0 | G85: =MIN(I85,K85,M85,Q85) -> 0
B86: trade | F86: =G86*0.93 -> 0 | G86: =MIN(I86,K86,M86,Q86) -> 0
B87: SUB-TOTAL | C87: =Estimate!#REF! -> #REF! | E87: =SUM(E82:E86) -> 0
B88: GENERAL CONDITIONS | C88: =C87*RFE!$F$20 -> #REF! | E88: =E87*RFE!$F$20 -> 0 | G88: =SUM(G81:G86)*RFE!$F$20 -> 1711
B89: INSURANCE | C89: =SUM(A81:A88)*RFE!$F$21 -> 0 | E89: =SUM(C81:C88)*RFE!$F$21 -> #REF! | G89: =SUM(G81:G88)*RFE!$F$21 -> 632.775
B90: FEE | C90: =SUM(A81:A89)*RFE!$F$22 -> 0 | E90: =SUM(C81:C89)*RFE!$F$22 -> #REF! | G90: =SUM(G81:G89)*RFE!$F$22 -> 843.17269
B91: TOTAL | C91: =SUM(C87:C90) -> #REF! | E91: =SUM(E87:E90) -> #REF! | G91: =SUM(G81:G90) -> 26786.948
B93: =Estimate!#REF! -> #REF!
B94: (Description)
B95: trade | F95: =G95*0.93 -> 0 | G95: =MIN(I95,K95,M95,Q95) -> 0
B96: trade | F96: =G96*0.93 -> 0 | G96: =MIN(I96,K96,M96,Q96) -> 0
B97: trade | F97: =G97*0.93 -> 0 | G97: =MIN(I97,K97,M97,Q97) -> 0
B98: trade | F98: =G98*0.93 -> 0 | G98: =MIN(I98,K98,M98,Q98) -> 0
B99: SUB-TOTAL | C99: =Estimate!#REF! -> #REF! | E99: =SUM(E94:E98) -> 0
B100: GENERAL CONDITIONS | C100: =C99*RFE!$F$20 -> #REF! | E100: =E99*RFE!$F$20 -> 0 | G100: =SUM(G93:G98)*RFE!$F$20 -> 0
B101: INSURANCE | C101: =SUM(A93:A100)*RFE!$F$21 -> 0 | E101: =SUM(C93:C100)*RFE!$F$21 -> #REF! | G101: =SUM(G93:G100)*RFE!$F$21 -> 0
B102: FEE | C102: =SUM(A93:A101)*RFE!$F$22 -> 0 | E102: =SUM(C93:C101)*RFE!$F$22 -> #REF! | G102: =SUM(G93:G101)*RFE!$F$22 -> 0
B103: TOTAL | C103: =SUM(C99:C102) -> #REF! | E103: =SUM(E99:E102) -> #REF! | G103: =SUM(G93:G102) -> 0
B105: =Estimate!#REF! -> #REF!
B106: (Description)
B107: trade | F107: =G107*0.93 -> 0 | G107: =MIN(I107,K107,M107,Q107) -> 0
B108: trade | F108: =G108*0.93 -> 0 | G108: =MIN(I108,K108,M108,Q108) -> 0
B109: trade | F109: =G109*0.93 -> 0 | G109: =MIN(I109,K109,M109,Q109) -> 0
B110: trade | F110: =G110*0.93 -> 0 | G110: =MIN(I110,K110,M110,Q110) -> 0
...

Sheet Sheet4

Sheet Kit
A2: Project: | B2: =RFE!C8 -> Town House Renovation | E2: Project #: | F2: =RFE!E14 -> 24-038C
A3: Location: | B3: =RFE!C9 -> 60 Bank Street | E3: Total S.F.:
A4: Duration | E4: Cost S.F.:
A5: Completion Date:
A7: CSI CODE | B7: DESCRIPTION | C7: PROPOSAL / BILLING AMOUNT | D7: P.O AMOUNT | E7: SUBCONTRACTOR / VENDOR | F7: P.O. # | G7: BUY OUT
A9: ='Summary Sheet '!A15 -> 2050 | B9: ='Summary Sheet '!B15 -> Demolition | C9: ='Summary Sheet '!#REF! -> #REF! | G9: =D9-C9 -> #REF! | I9: =ABS(C9+D9+G9) -> #REF!
A10: ='Summary Sheet '!A12 -> 2000 | B10: ='Summary Sheet '!B12 -> Excavation/Foundation | C10: ='Summary Sheet '!#REF! -> #REF! | G10: =D10-C10 -> #REF! | I10: =ABS(C10+D10+G10) -> #REF!
A11: ='Summary Sheet '!A16 -> 2090 | B11: ='Summary Sheet '!B16 -> Asbestos Removal | C11: ='Summary Sheet '!#REF! -> #REF! | G11: =D11-C11 -> #REF! | I11: =ABS(C11+D11+G11) -> #REF!
A12: ='Summary Sheet '!A18 -> 3000 | B12: ='Summary Sheet '!B18 -> Concrete | C12: ='Summary Sheet '!#REF! -> #REF! | G12: =D12-C12 -> #REF! | I12: =ABS(C12+D12+G12) -> #REF!
A13: ='Summary Sheet '!A19 -> 4000 | B13: ='Summary Sheet '!B19 -> Masonry | C13: ='Summary Sheet '!#REF! -> #REF! | G13: =D13-C13 -> #REF! | I13: =ABS(C13+D13+G13) -> #REF!
A14: ='Summary Sheet '!A21 -> 4500 | B14: ='Summary Sheet '!B21 -> Masonry Restoration | C14: ='Summary Sheet '!#REF! -> #REF! | G14: =D14-C14 -> #REF! | I14: =ABS(C14+D14+G14) -> #REF!
A15: ='Summary Sheet '!A22 -> 5120 | B15: ='Summary Sheet '!B22 -> Structural Steel | C15: ='Summary Sheet '!#REF! -> #REF! | G15: =D15-C15 -> #REF! | I15: =ABS(C15+D15+G15) -> #REF!
A16: ='Summary Sheet '!A24 -> 5500 | B16: ='Summary Sheet '!B24 -> Miscellaneous Iron | C16: ='Summary Sheet '!#REF! -> #REF! | G16: =D16-C16 -> #REF! | I16: =ABS(C16+D16+G16) -> #REF!
A17: ='Summary Sheet '!#REF! -> #REF! | B17: ='Summary Sheet '!#REF! -> #REF! | C17: ='Summary Sheet '!#REF! -> #REF! | G17: =D17-C17 -> #REF! | I17: =ABS(C17+D17+G17) -> #REF!
A18: ='Summary Sheet '!#REF! -> #REF! | B18: ='Summary Sheet '!#REF! -> #REF! | C18: ='Summary Sheet '!#REF! -> #REF! | G18: =D18-C18 -> #REF! | I18: =ABS(C18+D18+G18) -> #REF!
A19: ='Summary Sheet '!A25 -> 6400 | B19: ='Summary Sheet '!B25 -> Architectural Woodwork | C19: ='Summary Sheet '!#REF! -> #REF! | G19: =D19-C19 -> #REF! | I19: =ABS(C19+D19+G19) -> #REF!
A20: ='Summary Sheet '!#REF! -> #REF! | B20: ='Summary Sheet '!#REF! -> #REF! | C20: ='Summary Sheet '!#REF! -> #REF! | G20: =D20-C20 -> #REF! | I20: =ABS(C20+D20+G20) -> #REF!
A21: ='Summary Sheet '!A28 -> 7500 | B21: ='Summary Sheet '!B28 -> Roofing/Waterproofing | C21: ='Summary Sheet '!#REF! -> #REF! | G21: =D21-C21 -> #REF! | I21: =ABS(C21+D21+G21) -> #REF!
A22: ='Summary Sheet '!A29 -> 8110 | B22: ='Summary Sheet '!B29 -> Doors, Frames & Hardware | C22: ='Summary Sheet '!#REF! -> #REF! | G22: =D22-C22 -> #REF! | I22: =ABS(C22+D22+G22) -> #REF!
A23: ='Summary Sheet '!#REF! -> #REF! | B23: ='Summary Sheet '!#REF! -> #REF! | C23: ='Summary Sheet '!#REF! -> #REF! | G23: =D23-C23 -> #REF! | I23: =ABS(C23+D23+G23) -> #REF!
A24: ='Summary Sheet '!A31 -> 8520 | B24: ='Summary Sheet '!B31 -> Wood Windows | C24: ='Summary Sheet '!#REF! -> #REF! | G24: =D24-C24 -> #REF! | I24: =ABS(C24+D24+G24) -> #REF!
A25: ='Summary Sheet '!#REF! -> #REF! | B25: ='Summary Sheet '!#REF! -> #REF! | C25: ='Summary Sheet '!#REF! -> #REF! | G25: =D25-C25 -> #REF! | I25: =ABS(C25+D25+G25) -> #REF!
A26: ='Summary Sheet '!A32 -> 8800 | B26: ='Summary Sheet '!B32 -> Architectural Metal & Glass | C26: ='Summary Sheet '!#REF! -> #REF! | G26: =D26-C26 -> #REF! | I26: =ABS(C26+D26+G26) -> #REF!
A27: ='Summary Sheet '!A33 -> 8810 | B27: ='Summary Sheet '!B33 -> Window Film | C27: ='Summary Sheet '!#REF! -> #REF! | G27: =D27-C27 -> #REF! | I27: =ABS(C27+D27+G27) -> #REF!
A28: ='Summary Sheet '!A34 -> 8900 | B28: ='Summary Sheet '!B34 -> Window Walls | C28: ='Summary Sheet '!#REF! -> #REF! | G28: =D28-C28 -> #REF! | I28: =ABS(C28+D28+G28) -> #REF!
A29: ='Summary Sheet '!A35 -> 9250 | B29: ='Summary Sheet '!B35 -> Drywall & Carpentry | C29: ='Summary Sheet '!#REF! -> #REF! | G29: =D29-C29 -> #REF! | I29: =ABS(C29+D29+G29) -> #REF!
A30: ='Summary Sheet '!#REF! -> #REF! | B30: ='Summary Sheet '!#REF! -> #REF! | C30: ='Summary Sheet '!#REF! -> #REF! | G30: =D30-C30 -> #REF! | I30: =ABS(C30+D30+G30) -> #REF!
A31: ='Summary Sheet '!A36 -> 9300 | B31: ='Summary Sheet '!B36 -> Stone & Tile | C31: ='Summary Sheet '!#REF! -> #REF! | G31: =D31-C31 -> #REF! | I31: =ABS(C31+D31+G31) -> #REF!
A32: ='Summary Sheet '!#REF! -> #REF! | B32: ='Summary Sheet '!#REF! -> #REF! | C32: ='Summary Sheet '!#REF! -> #REF! | G32: =D32-C32 -> #REF! | I32: =ABS(C32+D32+G32) -> #REF!
A33: ='Summary Sheet '!A37 -> 9550 | B33: ='Summary Sheet '!B37 -> Wood Flooring | C33: ='Summary Sheet '!#REF! -> #REF! | G33: =D33-C33 -> #REF! | I33: =ABS(C33+D33+G33) -> #REF!
A34: ='Summary Sheet '!#REF! -> #REF! | B34: ='Summary Sheet '!#REF! -> #REF! | C34: ='Summary Sheet '!#REF! -> #REF! | G34: =D34-C34 -> #REF! | I34: =ABS(C34+D34+G34) -> #REF!
A35: ='Summary Sheet '!#REF! -> #REF! | B35: ='Summary Sheet '!#REF! -> #REF! | C35: ='Summary Sheet '!#REF! -> #REF! | G35: =D35-C35 -> #REF! | I35: =ABS(C35+D35+G35) -> #REF!
A36: ='Summary Sheet '!#REF! -> #REF! | B36: ='Summary Sheet '!#REF! -> #REF! | C36: ='Summary Sheet '!#REF! -> #REF! | G36: =D36-C36 -> #REF! | I36: =ABS(C36+D36+G36) -> #REF!
A37: ='Summary Sheet '!A40 -> 9900 | B37: ='Summary Sheet '!B40 -> Painting | C37: ='Summary Sheet '!#REF! -> #REF! | G37: =D37-C37 -> #REF! | I37: =ABS(C37+D37+G37) -> #REF!
A38: ='Summary Sheet '!#REF! -> #REF! | B38: ='Summary Sheet '!#REF! -> #REF! | C38: ='Summary Sheet '!#REF! -> #REF! | G38: =D38-C38 -> #REF! | I38: =ABS(C38+D38+G38) -> #REF!
A39: ='Summary Sheet '!#REF! -> #REF! | B39: ='Summary Sheet '!#REF! -> #REF! | C39: ='Summary Sheet '!#REF! -> #REF! | G39: =D39-C39 -> #REF! | I39: =ABS(C39+D39+G39) -> #REF!
A40: ='Summary Sheet '!#REF! -> #REF! | B40: ='Summary Sheet '!#REF! -> #REF! | C40: ='Summary Sheet '!#REF! -> #REF! | G40: =D40-C40 -> #REF! | I40: =ABS(C40+D40+G40) -> #REF!
A41: ='Summary Sheet '!#REF! -> #REF! | B41: ='Summary Sheet '!#REF! -> #REF! | C41: ='Summary Sheet '!#REF! -> #REF! | G41: =D41-C41 -> #REF! | I41: =ABS(C41+D41+G41) -> #REF!
A42: ='Summary Sheet '!A41 -> 10800 | B42: ='Summary Sheet '!B41 -> Toilet Accessories | C42: ='Summary Sheet '!#REF! -> #REF! | G42: =D42-C42 -> #REF! | I42: =ABS(C42+D42+G42) -> #REF!
A43: ='Summary Sheet '!#REF! -> #REF! | B43: ='Summary Sheet '!#REF! -> #REF! | C43: ='Summary Sheet '!#REF! -> #REF! | G43: =D43-C43 -> #REF! | I43: =ABS(C43+D43+G43) -> #REF!
A44: ='Summary Sheet '!#REF! -> #REF! | B44: ='Summary Sheet '!#REF! -> #REF! | C44: ='Summary Sheet '!#REF! -> #REF! | G44: =D44-C44 -> #REF! | I44: =ABS(C44+D44+G44) -> #REF!
A45: ='Summary Sheet '!#REF! -> #REF! | B45: ='Summary Sheet '!#REF! -> #REF! | C45: ='Summary Sheet '!#REF! -> #REF! | G45: =D45-C45 -> #REF! | I45: =ABS(C45+D45+G45) -> #REF!
A46: ='Summary Sheet '!#REF! -> #REF! | B46: ='Summary Sheet '!#REF! -> #REF! | C46: ='Summary Sheet '!#REF! -> #REF! | G46: =D46-C46 -> #REF! | I46: =ABS(C46+D46+G46) -> #REF!
A47: ='Summary Sheet '!#REF! -> #REF! | B47: ='Summary Sheet '!#REF! -> #REF! | C47: ='Summary Sheet '!#REF! -> #REF! | G47: =D47-C47 -> #REF! | I47: =ABS(C47+D47+G47) -> #REF!
A48: ='Summary Sheet '!#REF! -> #REF! | B48: ='Summary Sheet '!#REF! -> #REF! | C48: ='Summary Sheet '!#REF! -> #REF! | G48: =D48-C48 -> #REF! | I48: =ABS(C48+D48+G48) -> #REF!
A49: ='Summary Sheet '!A42 -> 11450 | B49: ='Summary Sheet '!B42 -> Appliances | C49: ='Summary Sheet '!#REF! -> #REF! | G49: =D49-C49 -> #REF! | I49: =ABS(C49+D49+G49) -> #REF!
A50: ='Summary Sheet '!A44 -> 12500 | B50: ='Summary Sheet '!B44 -> Window Treatment | C50: ='Summary Sheet '!#REF! -> #REF! | G50: =D50-C50 -> #REF! | I50: =ABS(C50+D50+G50) -> #REF!
A51: ='Summary Sheet '!A47 -> 14200 | B51: ='Summary Sheet '!B47 -> Elevator Work | C51: ='Summary Sheet '!#REF! -> #REF! | G51: =D51-C51 -> #REF! | I51: =ABS(C51+D51+G51) -> #REF!
A52: ='Summary Sheet '!#REF! -> #REF! | B52: ='Summary Sheet '!#REF! -> #REF! | C52: ='Summary Sheet '!#REF! -> #REF! | G52: =D52-C52 -> #REF! | I52: =ABS(C52+D52+G52) -> #REF!
A53: ='Summary Sheet '!A48 -> 15600 | B53: ='Summary Sheet '!B48 -> HVAC | C53: ='Summary Sheet '!#REF! -> #REF! | G53: =D53-C53 -> #REF! | I53: =ABS(C53+D53+G53) -> #REF!
A54: ='Summary Sheet '!#REF! -> #REF! | B54: ='Summary Sheet '!#REF! -> #REF! | C54: ='Summary Sheet '!#REF! -> #REF! | G54: =D54-C54 -> #REF! | I54: =ABS(C54+D54+G54) -> #REF!
A55: ='Summary Sheet '!A49 -> 15400 | B55: ='Summary Sheet '!B49 -> Plumbing | C55: ='Summary Sheet '!#REF! -> #REF! | G55: =D55-C55 -> #REF! | I55: =ABS(C55+D55+G55) -> #REF!
A56: ='Summary Sheet '!A51 -> 15500 | B56: ='Summary Sheet '!B51 -> Sprinklers | C56: ='Summary Sheet '!#REF! -> #REF! | G56: =D56-C56 -> #REF! | I56: =ABS(C56+D56+G56) -> #REF!
A57: ='Summary Sheet '!A54 -> 16500 | B57: ='Summary Sheet '!B54 -> Light Fixtures | C57: ='Summary Sheet '!#REF! -> #REF! | G57: =D57-C57 -> #REF! | I57: =ABS(C57+D57+G57) -> #REF!
A58: ='Summary Sheet '!A52 -> 16000 | B58: ='Summary Sheet '!B52 -> Electric | C58: ='Summary Sheet '!#REF! -> #REF! | G58: =D58-C58 -> #REF! | I58: =ABS(C58+D58+G58) -> #REF!
A59: ='Summary Sheet '!A55 -> 16300 | B59: ='Summary Sheet '!B55 -> Communications Cabling | C59: ='Summary Sheet '!#REF! -> #REF! | G59: =D59-C59 -> #REF! | I59: =ABS(C59+D59+G59) -> #REF!
A60: ='Summary Sheet '!#REF! -> #REF! | B60: ='Summary Sheet '!#REF! -> #REF! | C60: ='Summary Sheet '!#REF! -> #REF! | G60: =D60-C60 -> #REF! | I60: =ABS(C60+D60+G60) -> #REF!
A61: ='Summary Sheet '!A56 -> 17300 | B61: ='Summary Sheet '!B56 -> Security Systems | C61: ='Summary Sheet '!#REF! -> #REF! | G61: =D61-C61 -> #REF! | I61: =ABS(C61+D61+G61) -> #REF!
A62: ='Summary Sheet '!#REF! -> #REF! | B62: ='Summary Sheet '!#REF! -> #REF! | C62: ='Summary Sheet '!#REF! -> #REF! | G62: =D62-C62 -> #REF! | I62: =ABS(C62+D62+G62) -> #REF!
A63: ='Summary Sheet '!#REF! -> #REF! | B63: ='Summary Sheet '!#REF! -> #REF! | C63: ='Summary Sheet '!#REF! -> #REF! | G63: =D63-C63 -> #REF! | I63: =ABS(C63+D63+G63) -> #REF!
A64: ='Summary Sheet '!#REF! -> #REF! | B64: ='Summary Sheet '!#REF! -> #REF! | C64: ='Summary Sheet '!#REF! -> #REF! | G64: =D64-C64 -> #REF! | I64: =ABS(C64+D64+G64) -> #REF!
A65: ='Summary Sheet '!#REF! -> #REF! | B65: ='Summary Sheet '!#REF! -> #REF! | C65: ='Summary Sheet '!#REF! -> #REF! | G65: =D65-C65 -> #REF! | I65: =ABS(C65+D65+G65) -> #REF!
B66: ='Summary Sheet '!#REF! -> #REF! | C66: ='Summary Sheet '!#REF! -> #REF! | G66: =D66-C66 -> #REF! | I66: =ABS(C66+D66+G66) -> #REF!
B67: ='Summary Sheet '!#REF! -> #REF! | C67: ='Summary Sheet '!#REF! -> #REF! | G67: =D67-C67 -> #REF! | I67: =ABS(C67+D67+G67) -> #REF!
B68: ='Summary Sheet '!#REF! -> #REF! | C68: ='Summary Sheet '!#REF! -> #REF! | G68: =D68-C68 -> #REF! | I68: =ABS(C68+D68+G68) -> #REF!
B69: ='Summary Sheet '!#REF! -> #REF! | C69: ='Summary Sheet '!#REF! -> #REF! | G69: =D69-C69 -> #REF! | I69: =ABS(C69+D69+G69) -> #REF!
B70: ='Summary Sheet '!#REF! -> #REF! | C70: ='Summary Sheet '!#REF! -> #REF! | G70: =D70-C70 -> #REF! | I70: =ABS(C70+D70+G70) -> #REF!
B71: ='Summary Sheet '!#REF! -> #REF! | C71: ='Summary Sheet '!#REF! -> #REF! | G71: =D71-C71 -> #REF! | I71: =ABS(C71+D71+G71) -> #REF!
B72: ='Summary Sheet '!#REF! -> #REF! | C72: ='Summary Sheet '!#REF! -> #REF! | G72: =D72-C72 -> #REF! | I72: =ABS(C72+D72+G72) -> #REF!
B73: ='Summary Sheet '!#REF! -> #REF! | C73: ='Summary Sheet '!#REF! -> #REF! | G73: =D73-C73 -> #REF! | I73: =ABS(C73+D73+G73) -> #REF!
I74: =ABS(C74+D74+G74) -> 0
I75: =ABS(C75+D75+G75) -> 0
I76: =ABS(C76+D76+G76) -> 0
B77: TRADE COST | C77: =SUM(C9:C76) -> #REF! | D77: =SUM(D9:D76) -> 0 | G77: =SUM(G9:G76) -> #REF! | I77: =ABS(C77+D77+G77) -> #REF!
I78: =I83 -> #REF!
B79: GENERAL CONDITIONS | C79: =C77*RFE!F20 -> #REF! | I79: =ABS(C79+D79+G79) -> #REF!
B80: INSURANCE | C80: =SUM(C77:C79)*RFE!F21 -> #REF! | I80: =ABS(C80+D80+G80) -> #REF!
B81: FEE | C81: =SUM(C77:C80)*RFE!F22 -> #REF! | I81: =ABS(C81+D81+G81) -> #REF!
I82: =ABS(C82+D82+G82) -> 0
B83: AMOUNT OF CONTRACT | C83: =SUM(C77:C81) -> #REF! | I83: =ABS(C83+D83+G83) -> #REF!
C86: ='Summary Sheet '!E61 -> 5428499.1

Sheet RFI
A3: Job Name
A4: Street Address
A5: Town or Boro, State, Zip
A6: =CONCATENATE(RFE!D12, " Floor") -> Floor
A7: =CONCATENATE("Proposal #",RFE!F15) -> Proposal #
A8: Estimating RFI Log
B10: Below are RFIs regarding the above named project.
B11: Please furnish/clarify the following at your earliest convenience:
A13: 1 | C13: Sent | D13: Returned
A14: 2
A15: 3
A16: 4
A17: 5
A18: 6
A19: 7
A20: 8
A21: 9
A22: 10
A23: 11
A24: 12
A25: 13
... A37: 25

Sheet Sheet2
